vbmc4vsphere/__init__.py
vbmc4vsphere/config.py
vbmc4vsphere/control.py
vbmc4vsphere/exception.py
vbmc4vsphere/log.py
vbmc4vsphere/manager.py
vbmc4vsphere/utils.py
vbmc4vsphere/vbmc.py
vbmc4vsphere/cmd/__init__.py
vbmc4vsphere/cmd/vsbmc.py
vbmc4vsphere/cmd/vsbmcd.py
vbmc4vsphere-0.3.0.dist-info/AUTHORS
vbmc4vsphere-0.3.0.dist-info/LICENSE
vbmc4vsphere-0.3.0.dist-info/METADATA
vbmc4vsphere-0.3.0.dist-info/WHEEL
vbmc4vsphere-0.3.0.dist-info/entry_points.txt
vbmc4vsphere-0.3.0.dist-info/pbr.json
vbmc4vsphere-0.3.0.dist-info/top_level.txt
vbmc4vsphere-0.3.0.dist-info/RECORD
