Metadata-Version: 2.1
Name: vbmc4vsphere
Version: 0.3.0
Summary: Create virtual BMCs for controlling virtual instances via IPMI for vSphere environment
Home-page: https://github.com/kurokobo/virtualbmc-for-vsphere
Author: kurokobo
Author-email: 2920259+kurokobo@users.noreply.github.com
Classifier: Environment :: Other Environment
Classifier: Intended Audience :: Information Technology
Classifier: Intended Audience :: System Administrators
Classifier: License :: OSI Approved :: Apache Software License
Classifier: Operating System :: POSIX :: Linux
Classifier: Programming Language :: Python
Classifier: Programming Language :: Python :: Implementation :: CPython
Classifier: Programming Language :: Python :: 3 :: Only
Classifier: Programming Language :: Python :: 3
Classifier: Programming Language :: Python :: 3.6
Classifier: Programming Language :: Python :: 3.7
Classifier: Programming Language :: Python :: 3.8
Classifier: Programming Language :: Python :: 3.9
Classifier: Programming Language :: Python :: 3.10
Requires-Python: >=3.6
License-File: LICENSE
License-File: AUTHORS
Requires-Dist: pbr (!=2.1.0,>=2.0.0)
Requires-Dist: pyghmi (==1.5.16)
Requires-Dist: cliff (!=2.9.0,>=2.8.0)
Requires-Dist: pyzmq (>=14.3.1)
Requires-Dist: pyvmomi (>=7.0)
